{
    "development": {
        "server" : {"port" : 8080},
        "deploy" : "default.labs.dev",
        "mongodb" : "mongo://localhost/microcloud_dev",
        "redis" : {
            "host": "127.0.0.1",
            "dbName": 0
        },
        "metrics": {
            "client": "radim@laststation.net",
            "token": "dc101eb9dcde505831eebe653bc2a63353ec48b920a604db936d388db1bd9496"
        },
        "broker": "ipc:///tmp/mc.broker",
        "taskeng": "ipc:///tmp/taskeng",
        "compilation": {
                "user": "compile",
                "host": "176.34.236.201",
                "port": 22
            },
        "platform" :{
            "cache": false,
            "url": "http://api.labs.dev/",
            "token": "f933c346c502c11b64164143087f",
            "secret": "55347d223f161014a8659361afe771929f61246d09a3b22f"
        },        
        "microcloud": {            
            "gateway": {
                "host": "localhost",
                "port": 2222
            }
        }
    },
    "test": {},
    "production": {
        "server" : {"port" : 8080},
        "deploy" : "eu-1-aws.10xlabs.net",
        "mongodb" : "mongo://localhost/microcloud",
        "redis" : {
            "host": "127.0.0.1",
            "dbName": 0
        },
        "metrics": {
            "client": "radim@laststation.net",
            "token": "dc101eb9dcde505831eebe653bc2a63353ec48b920a604db936d388db1bd9496"
        },
        "broker": "ipc:///tmp/mc.broker",
        "platform" :{
            "cache": true,
            "url": "http://api.labs.internal/",
            "token": "f933c346c502c11b64164143087f",
            "secret": "55347d223f161014a8659361afe771929f61246d09a3b22f"
        },        
        "microcloud": {            
            "gateway": {
                "host": "ssh.eu-1-aws.10xlabs.net",
                "port": 22
            }
        }

    }
}
