{
    "development": {
        "server" : {
            "port" : 8080
        },
        "database" : {
            "host": "127.0.0.2",
            "port": 1234
        },
        "mongodb" : {
            "host" : "127.0.0.1",
            "dbName" : "microcloud_dev"
        },
        "redis" : {
            "host": "127.0.0.1",
            "dbName": 0
        },
        "broker": "ipc:///tmp/mc.broker",
        "taskeng": "ipc:///tmp/taskeng",
        "compilation": {
                "user": "compile",
                "host": "176.34.236.201",
                "port": 22
            }  
    },
    "test": {
        "server" : {
            "port" : 8081
        },
        "database" : {
            "host": "127.0.0.2",
            "port": 1234
        },
        "mongodb" : {
            "host" : "127.0.0.1",
            "dbName" : "microcloud_test"
        },
        "broker": "ipc:///tmp/mc.broker"
    },    
    "production": {
    }
}
